image_enhancement/__init__.py
image_enhancement/increase.py
image_eht-0.1.dist-info/METADATA
image_eht-0.1.dist-info/WHEEL
image_eht-0.1.dist-info/top_level.txt
image_eht-0.1.dist-info/RECORD
